odoo/addons/pos_order_to_sale_order_delivery/README.rst
odoo/addons/pos_order_to_sale_order_delivery/__init__.py
odoo/addons/pos_order_to_sale_order_delivery/__manifest__.py
odoo/addons/pos_order_to_sale_order_delivery/i18n/es.po
odoo/addons/pos_order_to_sale_order_delivery/i18n/it.po
odoo/addons/pos_order_to_sale_order_delivery/i18n/pos_order_to_sale_order_delivery.pot
odoo/addons/pos_order_to_sale_order_delivery/models/__init__.py
odoo/addons/pos_order_to_sale_order_delivery/models/delivery_carrier.py
odoo/addons/pos_order_to_sale_order_delivery/models/pos_config.py
odoo/addons/pos_order_to_sale_order_delivery/models/res_config_settings.py
odoo/addons/pos_order_to_sale_order_delivery/models/sale_order.py
odoo/addons/pos_order_to_sale_order_delivery/readme/CONFIGURE.rst
odoo/addons/pos_order_to_sale_order_delivery/readme/CONTRIBUTORS.rst
odoo/addons/pos_order_to_sale_order_delivery/readme/DESCRIPTION.rst
odoo/addons/pos_order_to_sale_order_delivery/readme/USAGE.rst
odoo/addons/pos_order_to_sale_order_delivery/static/description/icon.png
odoo/addons/pos_order_to_sale_order_delivery/static/description/index.html
odoo/addons/pos_order_to_sale_order_delivery/static/img/pos_add_shipping.png
odoo/addons/pos_order_to_sale_order_delivery/static/img/pos_config.png
odoo/addons/pos_order_to_sale_order_delivery/static/img/pos_select_shipping.png
odoo/addons/pos_order_to_sale_order_delivery/static/src/css/pos.css
odoo/addons/pos_order_to_sale_order_delivery/static/src/js/models.esm.js
odoo/addons/pos_order_to_sale_order_delivery/static/src/js/Popups/ChooseDeliveryCarrierPopup.esm.js
odoo/addons/pos_order_to_sale_order_delivery/static/src/js/Popups/CreateOrderPopup.esm.js
odoo/addons/pos_order_to_sale_order_delivery/static/src/xml/Popups/ChooseDeliveryCarrierPopup.xml
odoo/addons/pos_order_to_sale_order_delivery/static/src/xml/Popups/CreateOrderPopup.xml
odoo/addons/pos_order_to_sale_order_delivery/views/res_config_settings_view.xml
odoo_addon_pos_order_to_sale_order_delivery-16.0.1.0.1.2.dist-info/METADATA
odoo_addon_pos_order_to_sale_order_delivery-16.0.1.0.1.2.dist-info/WHEEL
odoo_addon_pos_order_to_sale_order_delivery-16.0.1.0.1.2.dist-info/top_level.txt
odoo_addon_pos_order_to_sale_order_delivery-16.0.1.0.1.2.dist-info/RECORD
